mokapot/__init__.py
mokapot/brew.py
mokapot/confidence.py
mokapot/config.py
mokapot/dataset.py
mokapot/model.py
mokapot/mokapot.py
mokapot/peptides.py
mokapot/picked_protein.py
mokapot/proteins.py
mokapot/qvalues.py
mokapot/utils.py
mokapot/parsers/__init__.py
mokapot/parsers/fasta.py
mokapot/parsers/pepxml.py
mokapot/parsers/pin.py
mokapot/plugins/__init__.py
mokapot/writers/__init__.py
mokapot/writers/flashlfq.py
mokapot/writers/txt.py
tests/__init__.py
tests/conftest.py
tests/unit_tests/__init__.py
tests/unit_tests/test_brew.py
tests/unit_tests/test_confidence.py
tests/unit_tests/test_dataset.py
tests/unit_tests/test_model.py
tests/unit_tests/test_mokapot.py
tests/unit_tests/test_parser_pepxml.py
tests/unit_tests/test_parser_pin.py
tests/unit_tests/test_peptides.py
tests/unit_tests/test_picked_protein.py
tests/unit_tests/test_proteins.py
tests/unit_tests/test_qvalues.py
tests/unit_tests/test_utils.py
tests/unit_tests/test_version.py
tests/unit_tests/test_writer_flashlfq.py
tests/unit_tests/test_writer_txt.py
mokapot-0.10.0.dist-info/LICENSE
mokapot-0.10.0.dist-info/METADATA
mokapot-0.10.0.dist-info/WHEEL
mokapot-0.10.0.dist-info/entry_points.txt
mokapot-0.10.0.dist-info/top_level.txt
mokapot-0.10.0.dist-info/RECORD
