Metadata-Version: 2.1
Name: mokapot
Version: 0.10.0
Summary: Fast and flexible semi-supervised learning for peptide detection
Author-email: "William E. Fondrie" <fondriew@gmail.com>
License: Apache 2.0
Project-URL: Homepage, https://github.com/wfondrie/mokapot
Project-URL: Documentation, https://mokapot.readthedocs.io
Project-URL: Bug Tracker, https://github.com/wfondrie/mokapot/issues
Project-URL: Discussion Board, https://github.com/wfondrie/mokapot/discussions
Classifier: Programming Language :: Python :: 3
Classifier: License :: OSI Approved :: Apache Software License
Classifier: Operating System :: OS Independent
Classifier: Topic :: Scientific/Engineering :: Bio-Informatics
Requires-Python: >=3.6
License-File: LICENSE
Requires-Dist: numpy >=1.18.1
Requires-Dist: pandas >=1.0.3
Requires-Dist: scikit-learn >=0.22.1
Requires-Dist: numba >=0.48.0
Requires-Dist: matplotlib >=3.1.3
Requires-Dist: lxml >=4.6.2
Requires-Dist: triqler >=0.6.2
Requires-Dist: joblib >=1.1.0
Requires-Dist: importlib-metadata >=5.1.0
Provides-Extra: dev
Requires-Dist: pre-commit >=2.7.1 ; extra == 'dev'
Requires-Dist: black >=19.10b0 ; extra == 'dev'
Provides-Extra: docs
Requires-Dist: numpydoc >=1.0.0 ; extra == 'docs'
Requires-Dist: sphinx-argparse >=0.2.5 ; extra == 'docs'
Requires-Dist: sphinx-rtd-theme >=0.5.0 ; extra == 'docs'
Requires-Dist: nbsphinx >=0.7.1 ; extra == 'docs'
Requires-Dist: ipykernel >=5.3.0 ; extra == 'docs'
Requires-Dist: recommonmark >=0.5.0 ; extra == 'docs'
